UtcTimeTool/__init__.py
UtcTimeTool/timetools.py
UtcTimeTool/timezone_data.json
UtcTimeTool/timezones.py
UtcTimeTool/utils.py
UtcTimeTool-0.3.1.dist-info/LICENSE
UtcTimeTool-0.3.1.dist-info/METADATA
UtcTimeTool-0.3.1.dist-info/WHEEL
UtcTimeTool-0.3.1.dist-info/top_level.txt
UtcTimeTool-0.3.1.dist-info/RECORD
