Metadata-Version: 2.1
Name: UtcTimeTool
Version: 0.3.1
Summary: A tool to retrieve UTC timezones by country.
Home-page: https://github.com/yourusername/UtcTimeTool
Author: PC BAZ
Author-email: pc.baz1617@gmail.com
Classifier: Programming Language :: Python :: 3
Classifier: License :: OSI Approved :: MIT License
Classifier: Operating System :: OS Independent
Requires-Python: >=3.6
License-File: LICENSE
